setup.cfg
setup.py
pytplinkrouter/__init__.py
pytplinkrouter/__main__.py
pytplinkrouter.egg-info/PKG-INFO
pytplinkrouter.egg-info/SOURCES.txt
pytplinkrouter.egg-info/dependency_links.txt
pytplinkrouter.egg-info/requires.txt
pytplinkrouter.egg-info/top_level.txt
pytplinkrouter.egg-info/zip-safe