Metadata-Version: 1.0
Name: pytplinkrouter
Version: 0.1.0
Summary: Access TPLink routers
Home-page: http://github.com/ericpignet/pytplinkrouter
Author: Eric Pignet
Author-email: eric@erixpage.com
License: MIT
Platform: UNKNOWN
